mcu_web_api/__init__.py
mcu_web_api/fast_api_server.py
mcu_web_api/routes/__init__.py
mcu_web_api/routes/ejector_routes.py
mcu_web_api/routes/io_routes.py
mcu_web_api/routes/mcu_routes.py
mcu_web_api/routes/motor_routes.py
mcu_web_api/routes/sensor_routes.py
mcu_web_api/routes/trigger_routes.py
mcu_web_api/routes/unit_test_routes.py
mcu_communication_web_api_server-1.0.5.dist-info/METADATA
mcu_communication_web_api_server-1.0.5.dist-info/WHEEL
mcu_communication_web_api_server-1.0.5.dist-info/top_level.txt
mcu_communication_web_api_server-1.0.5.dist-info/RECORD
